MANIFEST.in
README.md
pyproject.toml
setup.cfg
setup.py
emmer/__init__.py
emmer/main.py
emmer.egg-info/PKG-INFO
emmer.egg-info/SOURCES.txt
emmer.egg-info/dependency_links.txt
emmer.egg-info/entry_points.txt
emmer.egg-info/not-zip-safe
emmer.egg-info/requires.txt
emmer.egg-info/top_level.txt
emmer/include/__init__.py
emmer/include/emmer_utils.py
emmer/include/geckodriver
emmer/include/theoretical_profiles.pickle
emmer/include/confidenceMapUtil/FDRutil.py
emmer/include/confidenceMapUtil/__init__.py
emmer/include/confidenceMapUtil/confidenceMapMain.py
emmer/include/confidenceMapUtil/locscaleUtil.py
emmer/include/confidenceMapUtil/mapUtil.py
emmer/ndimage/__init__.py
emmer/ndimage/average_half_maps.py
emmer/ndimage/compute_real_space_correlation.py
emmer/ndimage/get_center_of_mass.py
emmer/ndimage/map_tools.py
emmer/ndimage/map_utils.py
emmer/ndimage/plotContourMap.py
emmer/ndimage/trim_map_between_residues.py
emmer/ndimage/bfactors/__init__.py
emmer/ndimage/bfactors/estimate_bfactor_distribution.py
emmer/ndimage/bfactors/estimate_bfactor_map.py
emmer/ndimage/bfactors/estimate_local_bfactor.py
emmer/ndimage/contour/__init__.py
emmer/ndimage/contour/contour_utils.py
emmer/ndimage/contour/count_segments.py
emmer/ndimage/contour/surface_area_at_threshold.py
emmer/ndimage/contour/volume_at_threshold.py
emmer/ndimage/contour/volume_matching_threshold.py
emmer/ndimage/filter/__init__.py
emmer/ndimage/filter/apply_fsc_filter.py
emmer/ndimage/filter/band_pass_filter.py
emmer/ndimage/filter/filter_utils.py
emmer/ndimage/filter/high_pass_filter.py
emmer/ndimage/filter/low_pass_filter.py
emmer/ndimage/filter/smoothen_mask.py
emmer/ndimage/fsc/__init__.py
emmer/ndimage/fsc/calculate_fsc_curve.py
emmer/ndimage/fsc/calculate_phase_correlation.py
emmer/ndimage/fsc/compute_fsc_resolution.py
emmer/ndimage/fsc/fsc_utils.py
emmer/ndimage/mask/__init__.py
emmer/ndimage/mask/compute_confidence_map.py
emmer/ndimage/mask/get_atomic_model_mask.py
emmer/ndimage/mask/get_spherical_mask.py
emmer/ndimage/mask/mask_utils.py
emmer/ndimage/plots/__init__.py
emmer/ndimage/plots/plotContourMap.py
emmer/ndimage/plots/plots.py
emmer/ndimage/radial_profile/__init__.py
