Metadata-Version: 2.1
Name: emmer
Version: 0.1.2
Summary: A python toolkit for the cryo-EM developer
Home-page: https://gitlab.tudelft.nl/aj-lab/emmer
Author: Alok Bharadwaj, Maarten Joosten, Stefan T Huber, Arjen Jakobi, Reinier de Bruin
License: 3-clause BSD
Requires-Dist: numpy>=1.19.5
Requires-Dist: scipy>=1.5.4
Requires-Dist: pandas>=1.1.5
Requires-Dist: mrcfile>=1.3.0
Requires-Dist: gemmi>=0.4.8
Requires-Dist: pypdb>=2.0
Requires-Dist: scikit-learn>=0.0
Requires-Dist: pwlf>=2.0.4
Requires-Dist: tqdm>=4.62.3
Requires-Dist: more_itertools>=8.10.0
Requires-Dist: scikit-image>=0.17.2
Requires-Dist: biopython==1.78
Requires-Dist: matplotlib==3.5.1
Requires-Dist: coverage
Requires-Dist: pyfiglet>=0.8.post1
Requires-Dist: wget>=3.2
